README.rst
setup.py
uaparser/__init__.py
uaparser/test.py
uaparser.egg-info/PKG-INFO
uaparser.egg-info/SOURCES.txt
uaparser.egg-info/dependency_links.txt
uaparser.egg-info/top_level.txt