Metadata-Version: 1.1
Name: uaparser
Version: 0.1.0
Summary: Library for parsing browser user agents
Home-page: https://github.com/ojarva/ua-detection-python
Author: Olli Jarva
Author-email: olli@jarva.fi
License: MIT
Download-URL: https://github.com/ojarva/ua-detection-python
Keywords: browser user-agent parser
Platform: UNKNOWN
Classifier: Development Status :: 3 - Alpha
Classifier: Topic :: Software Development :: Libraries
Classifier: License :: OSI Approved :: MIT License
